CS.v
`timescale 1ns/10ps
/*
 * IC Contest Computational System (CS)
*/
module CS(Y, X, reset, clk);

input clk, reset; 
input [7:0] X;
output reg [9:0] Y;
reg [3:0]count;
reg [7:0]buffer[8:0];

wire [10:0]avg;
wire [7:0]smaller0, smaller1, smaller2, smaller3, smaller4, smaller5, smaller6, smaller7, smaller8, 
          com01, com23, com45, com67, 
          com03, com47,
          com07, com8;        
integer i;

assign avg = (buffer[0] + buffer[1] + buffer[2] + buffer[3] + buffer[4] + buffer[5] + buffer[6] + buffer[7] + buffer[8])/9; 

assign smaller0 = (buffer[0] <= avg)?buffer[0]:8'd0;
assign smaller1 = (buffer[1] <= avg)?buffer[1]:8'd0;
assign smaller2 = (buffer[2] <= avg)?buffer[2]:8'd0;
assign smaller3 = (buffer[3] <= avg)?buffer[3]:8'd0;
assign smaller4 = (buffer[4] <= avg)?buffer[4]:8'd0;
assign smaller5 = (buffer[5] <= avg)?buffer[5]:8'd0;
assign smaller6 = (buffer[6] <= avg)?buffer[6]:8'd0;
assign smaller7 = (buffer[7] <= avg)?buffer[7]:8'd0;
assign smaller8 = (buffer[8] <= avg)?buffer[8]:8'd0;

assign com01 = (smaller0 > smaller1)?smaller0:smaller1;
assign com23 = (smaller2 > smaller3)?smaller2:smaller3;
assign com45 = (smaller4 > smaller5)?smaller4:smaller5;
assign com67 = (smaller6 > smaller7)?smaller6:smaller7;

assign com03 = (com01 > com23)?com01:com23;
assign com47 = (com45 > com67)?com45:com67;

assign com07 = (com03 > com47)?com03:com47;

assign com8 = (com07 > smaller8)?com07:smaller8;

// find < avg from buffer and find the maximum 
always@(posedge clk)
begin
  if(reset)
    begin
      for(i = 0; i < 9; i = i + 1)
        buffer[i] <= 8'd0;    
  end  
  else
    begin
      for(i = 0; i < 8; i = i + 1)
          buffer[i+1] <= buffer[i]; 
      buffer[0] <= X;
  end
end
always@(negedge clk)
begin
  if(reset)
    begin
      count <= 4'd0; 
      Y <= 10'd0; 
  end  
  else
    begin
      if(count != 4'd8)
        begin     
          Y <= 10'd0;  
          count <= count + 4'd1;  
      end
      else
        begin
          count <= count;
          //if(buffer[0] == avg || buffer[1] == avg || buffer[2] == avg || buffer[3] == avg || buffer[4] == avg || buffer[5] == avg || buffer[6] == avg || buffer[7] == avg || buffer[8] == avg)
            //Y <= (((buffer[0] + buffer[1]) + (buffer[2] + buffer[3])) + ((buffer[4] + buffer[5]) + (buffer[6] + buffer[7])) + (buffer[8] + (avg * 9))) >> 3;
          //else
            //begin
                Y <= (buffer[0] + buffer[1] + buffer[2] + buffer[3] + buffer[4] + buffer[5] + buffer[6] + buffer[7] + buffer[8] + (com8 * 9)) >> 3;
          //end
      end
  end
end
endmodule

testfixture.v
`timescale 1ns/10ps
`define CYCLE 10        	// Modify your clock period here
`define SDFFILE "cs_syn.sdf"	// Modify your sdf file name
`define INFILE "in.dat"
`define OUTFILE "out_golden.dat"  

module test;
parameter INPUT_DATA = `INFILE;
parameter GOLDEN = `OUTFILE;
parameter N_PAT = 2000;
parameter t_reset = `CYCLE*2;

reg reset;
reg clk;
reg ready;
reg stop;
reg flag1, flag2;
wire pclk = clk ;

integer i, out_f, err, pattern_num;
integer a, b;
reg     [7:0] X;
reg 	[7:0] data_base1 [0:20000];
reg	[9:0] data_base2 [0:20000];
reg 	[9:0] data_tmp;
wire    [9:0] Y; 

CS top (.Y(Y), .X(X), .reset(reset), .clk(clk)); 

//initial $sdf_annotate(`SDFFILE, top);

initial	$readmemh (INPUT_DATA, data_base1);

initial $readmemh (GOLDEN, data_base2);

initial begin
   reset = 1'b0;
   clk = 1'b1;
   stop = 1'b0;
   err = 0;
   a = 0;
   b = 0;
   pattern_num = 0 ;     
end

initial begin
$dumpfile("cs.vcd");
$dumpvars;
//$fsdbDumpfile("cs.fsdb");
//$fsdbDumpvars; 

   out_f = $fopen("out.dat");
   if (out_f == 0) begin
        $display("Output file open error !");
        $finish;
   end
end

always begin #(`CYCLE/2) clk = ~clk;
end


specify
$setup(Y, posedge pclk, 0.5, flag1);
$hold(posedge pclk, Y, 0.5, flag2); 
endspecify 

always @(flag1)
   if(flag1 == 1'b1 || flag1 == 1'b0)
     a = a +1;

always @(flag2)
   if(flag2 == 1'b1  || flag2 == 1'b0)
     b = b +1;


initial 
  begin
    X = data_base1[0] ;
    @(negedge clk) reset = 1'b1;
    #t_reset reset = 1'b0;  ready = 1'b0;
    #`CYCLE
    for (i = 1; i < N_PAT; i = i + 1) 
    begin
      @(negedge clk) X = data_base1[i]; 
      if (i==8)
        @(posedge clk) ready = 1'b1;                      
    end 
  end  
 		
always @(posedge clk) 
  begin
   if (pattern_num + 9 > N_PAT)      stop = 1 ;
   else if (ready) 
     begin
       data_tmp = data_base2[pattern_num]; 
       $fdisplay(out_f,"%h", Y); 
         if (Y !== data_tmp) 
           begin
             $display("ERROR at %d:output %h !=expect %h ",pattern_num, Y, data_tmp);
             err = err + 1 ;
           end
       pattern_num = pattern_num + 1 ; 
     end

  end  

initial begin
      @(posedge stop)
      $display("---------------------------------------------\n");
      if (a !=0)
         $display("There are %d setup time violations by Y\n", a);
      if (b !=0)
         $display("There are %d hold time violations by Y\n", b);
      $display("---------------------------------------------\n");
      if (err == 0)
        begin
          $display("All data have been generated successfully!\n");
          $display("-------------------PASS-------------------\n");
        end
      else 
         $display("There are %d errors!\n", err);
      $display("---------------------------------------------\n");
      $finish;
   end
endmodule

cs.vcd
$date
	Fri Jul 31 18:51:44 2020
$end
$version
	ModelSim Version 10.1c
$end
$timescale
	10ps
$end
$scope module test $end
$var parameter 48 ! INPUT_DATA $end
$var parameter 112 " GOLDEN $end
$var parameter 32 # N_PAT $end
$var parameter 32 $ t_reset $end
$var reg 1 % reset $end
$var reg 1 & clk $end
$var reg 1 ' ready $end
$var reg 1 ( stop $end
$var reg 1 ) flag1 $end
$var reg 1 * flag2 $end
$var wire 1 + pclk $end
$var integer 32 , i $end
$var integer 32 - out_f $end
$var integer 32 . err $end
$var integer 32 / pattern_num $end
$var integer 32 0 a $end
$var integer 32 1 b $end
$var reg 8 2 X [7:0] $end
$var reg 10 3 data_tmp [9:0] $end
$var wire 1 4 Y [9] $end
$var wire 1 5 Y [8] $end
$var wire 1 6 Y [7] $end
$var wire 1 7 Y [6] $end
$var wire 1 8 Y [5] $end
$var wire 1 9 Y [4] $end
$var wire 1 : Y [3] $end
$var wire 1 ; Y [2] $end
$var wire 1 < Y [1] $end
$var wire 1 = Y [0] $end
$scope module top $end
$var wire 1 > clk $end
$var wire 1 ? reset $end
$var wire 1 @ X [7] $end
$var wire 1 A X [6] $end
$var wire 1 B X [5] $end
$var wire 1 C X [4] $end
$var wire 1 D X [3] $end
$var wire 1 E X [2] $end
$var wire 1 F X [1] $end
$var wire 1 G X [0] $end
$var reg 10 H Y [9:0] $end
$var reg 4 I count [3:0] $end
$var wire 1 J avg [10] $end
$var wire 1 K avg [9] $end
$var wire 1 L avg [8] $end
$var wire 1 M avg [7] $end
$var wire 1 N avg [6] $end
$var wire 1 O avg [5] $end
$var wire 1 P avg [4] $end
$var wire 1 Q avg [3] $end
$var wire 1 R avg [2] $end
$var wire 1 S avg [1] $end
$var wire 1 T avg [0] $end
$var wire 1 U smaller0 [7] $end
$var wire 1 V smaller0 [6] $end
$var wire 1 W smaller0 [5] $end
$var wire 1 X smaller0 [4] $end
$var wire 1 Y smaller0 [3] $end
$var wire 1 Z smaller0 [2] $end
$var wire 1 [ smaller0 [1] $end
$var wire 1 \ smaller0 [0] $end
$var wire 1 ] smaller1 [7] $end
$var wire 1 ^ smaller1 [6] $end
$var wire 1 _ smaller1 [5] $end
$var wire 1 ` smaller1 [4] $end
$var wire 1 a smaller1 [3] $end
$var wire 1 b smaller1 [2] $end
$var wire 1 c smaller1 [1] $end
$var wire 1 d smaller1 [0] $end
$var wire 1 e smaller2 [7] $end
$var wire 1 f smaller2 [6] $end
$var wire 1 g smaller2 [5] $end
$var wire 1 h smaller2 [4] $end
$var wire 1 i smaller2 [3] $end
$var wire 1 j smaller2 [2] $end
$var wire 1 k smaller2 [1] $end
$var wire 1 l smaller2 [0] $end
$var wire 1 m smaller3 [7] $end
$var wire 1 n smaller3 [6] $end
$var wire 1 o smaller3 [5] $end
$var wire 1 p smaller3 [4] $end
$var wire 1 q smaller3 [3] $end
$var wire 1 r smaller3 [2] $end
$var wire 1 s smaller3 [1] $end
$var wire 1 t smaller3 [0] $end
$var wire 1 u smaller4 [7] $end
$var wire 1 v smaller4 [6] $end
$var wire 1 w smaller4 [5] $end
$var wire 1 x smaller4 [4] $end
$var wire 1 y smaller4 [3] $end
$var wire 1 z smaller4 [2] $end
$var wire 1 { smaller4 [1] $end
$var wire 1 | smaller4 [0] $end
$var wire 1 } smaller5 [7] $end
$var wire 1 ~ smaller5 [6] $end
$var wire 1 !! smaller5 [5] $end
$var wire 1 "! smaller5 [4] $end
$var wire 1 #! smaller5 [3] $end
$var wire 1 $! smaller5 [2] $end
$var wire 1 %! smaller5 [1] $end
$var wire 1 &! smaller5 [0] $end
$var wire 1 '! smaller6 [7] $end
$var wire 1 (! smaller6 [6] $end
$var wire 1 )! smaller6 [5] $end
$var wire 1 *! smaller6 [4] $end
$var wire 1 +! smaller6 [3] $end
$var wire 1 ,! smaller6 [2] $end
$var wire 1 -! smaller6 [1] $end
$var wire 1 .! smaller6 [0] $end
$var wire 1 /! smaller7 [7] $end
$var wire 1 0! smaller7 [6] $end
$var wire 1 1! smaller7 [5] $end
$var wire 1 2! smaller7 [4] $end
$var wire 1 3! smaller7 [3] $end
$var wire 1 4! smaller7 [2] $end
$var wire 1 5! smaller7 [1] $end
$var wire 1 6! smaller7 [0] $end
$var wire 1 7! smaller8 [7] $end
$var wire 1 8! smaller8 [6] $end
$var wire 1 9! smaller8 [5] $end
$var wire 1 :! smaller8 [4] $end
$var wire 1 ;! smaller8 [3] $end
$var wire 1 <! smaller8 [2] $end
$var wire 1 =! smaller8 [1] $end
$var wire 1 >! smaller8 [0] $end
$var wire 1 ?! com01 [7] $end
$var wire 1 @! com01 [6] $end
$var wire 1 A! com01 [5] $end
$var wire 1 B! com01 [4] $end
$var wire 1 C! com01 [3] $end
$var wire 1 D! com01 [2] $end
$var wire 1 E! com01 [1] $end
$var wire 1 F! com01 [0] $end
$var wire 1 G! com23 [7] $end
$var wire 1 H! com23 [6] $end
$var wire 1 I! com23 [5] $end
$var wire 1 J! com23 [4] $end
$var wire 1 K! com23 [3] $end
$var wire 1 L! com23 [2] $end
$var wire 1 M! com23 [1] $end
$var wire 1 N! com23 [0] $end
$var wire 1 O! com45 [7] $end
$var wire 1 P! com45 [6] $end
$var wire 1 Q! com45 [5] $end
$var wire 1 R! com45 [4] $end
$var wire 1 S! com45 [3] $end
$var wire 1 T! com45 [2] $end
$var wire 1 U! com45 [1] $end
$var wire 1 V! com45 [0] $end
$var wire 1 W! com67 [7] $end
$var wire 1 X! com67 [6] $end
$var wire 1 Y! com67 [5] $end
$var wire 1 Z! com67 [4] $end
$var wire 1 [! com67 [3] $end
$var wire 1 \! com67 [2] $end
$var wire 1 ]! com67 [1] $end
$var wire 1 ^! com67 [0] $end
$var wire 1 _! com03 [7] $end
$var wire 1 `! com03 [6] $end
$var wire 1 a! com03 [5] $end
$var wire 1 b! com03 [4] $end
$var wire 1 c! com03 [3] $end
$var wire 1 d! com03 [2] $end
$var wire 1 e! com03 [1] $end
$var wire 1 f! com03 [0] $end
$var wire 1 g! com47 [7] $end
$var wire 1 h! com47 [6] $end
$var wire 1 i! com47 [5] $end
$var wire 1 j! com47 [4] $end
$var wire 1 k! com47 [3] $end
$var wire 1 l! com47 [2] $end
$var wire 1 m! com47 [1] $end
$var wire 1 n! com47 [0] $end
$var wire 1 o! com07 [7] $end
$var wire 1 p! com07 [6] $end
$var wire 1 q! com07 [5] $end
$var wire 1 r! com07 [4] $end
$var wire 1 s! com07 [3] $end
$var wire 1 t! com07 [2] $end
$var wire 1 u! com07 [1] $end
$var wire 1 v! com07 [0] $end
$var wire 1 w! com8 [7] $end
$var wire 1 x! com8 [6] $end
$var wire 1 y! com8 [5] $end
$var wire 1 z! com8 [4] $end
$var wire 1 {! com8 [3] $end
$var wire 1 |! com8 [2] $end
$var wire 1 }! com8 [1] $end
$var wire 1 ~! com8 [0] $end
$var integer 32 !" i $end
$upscope $end
$upscope $end
$enddefinitions $end
#0
$dumpvars
0%
1&
x'
0(
x)
x*
b10001111 2
bx 3
bx H
bx I
b11111010000 #
b10100 $
b11010010110111000101110011001000110000101110100 !
b110111101110101011101000101111101100111011011110110110001100100011001010110111000101110011001000110000101110100 "
bx ,
b10 -
b0 .
b0 /
b0 0
b0 1
b1000 !"
1+
x=
x<
x;
x:
x9
x8
x7
x6
x5
x4
xT
xS
xR
xQ
xP
xO
xN
xM
xL
xK
xJ
x\
x[
xZ
xY
0X
0W
0V
xU
xd
xc
xb
xa
x`
x_
x^
x]
xl
xk
xj
xi
xh
xg
xf
xe
xt
xs
xr
xq
xp
xo
xn
xm
x|
x{
xz
xy
xx
xw
xv
xu
x&!
x%!
x$!
x#!
x"!
x!!
x~
x}
x.!
x-!
x,!
x+!
x*!
x)!
x(!
x'!
x6!
x5!
x4!
x3!
x2!
x1!
x0!
x/!
x>!
x=!
x<!
x;!
x:!
x9!
x8!
x7!
xF!
xE!
xD!
xC!
xB!
xA!
x@!
x?!
xN!
xM!
xL!
xK!
xJ!
xI!
xH!
xG!
xV!
xU!
xT!
xS!
xR!
xQ!
xP!
xO!
x^!
x]!
x\!
x[!
xZ!
xY!
xX!
xW!
xf!
xe!
xd!
xc!
xb!
xa!
x`!
x_!
xn!
xm!
xl!
xk!
xj!
xi!
xh!
xg!
xv!
xu!
xt!
xs!
xr!
xq!
xp!
xo!
x~!
x}!
x|!
x{!
xz!
xy!
xx!
xw!
1>
0?
1G
1F
1E
1D
0C
0B
0A
1@
$end
#500
0&
0+
0>
1%
1?
#1000
1&
1+
1>
b0 !"
b1 !"
b10 !"
b11 !"
b100 !"
b101 !"
b110 !"
b111 !"
b1000 !"
b1001 !"
0T
0S
0R
0Q
0P
0O
0N
0M
0L
0K
0J
0\
0[
0Z
0Y
0U
0d
0c
0b
0a
0`
0_
0^
0]
0l
0k
0j
0i
0h
0g
0f
0e
0t
0s
0r
0q
0p
0o
0n
0m
0|
0{
0z
0y
0x
0w
0v
0u
0&!
0%!
0$!
0#!
0"!
0!!
0~
0}
0.!
0-!
0,!
0+!
0*!
0)!
0(!
0'!
06!
05!
04!
03!
02!
01!
00!
0/!
0>!
0=!
0<!
0;!
0:!
09!
08!
07!
0^!
0]!
0\!
0[!
0Z!
0Y!
0X!
0W!
0V!
0U!
0T!
0S!
0R!
0Q!
0P!
0O!
0N!
0M!
0L!
0K!
0J!
0I!
0H!
0G!
0F!
0E!
0D!
0C!
0B!
0A!
0@!
0?!
0f!
0e!
0d!
0c!
0b!
0a!
0`!
0_!
0n!
0m!
0l!
0k!
0j!
0i!
0h!
0g!
0v!
0u!
0t!
0s!
0r!
0q!
0p!
0o!
0~!
0}!
0|!
0{!
0z!
0y!
0x!
0w!
#1500
0&
0+
0>
b0 I
b0 H
0=
0<
0;
0:
09
08
07
06
05
04
#2000
1&
1+
1>
b0 !"
b1 !"
b10 !"
b11 !"
b100 !"
b101 !"
b110 !"
b111 !"
b1000 !"
b1001 !"
#2500
0%
0'
0&
0?
0+
0>
b1 I
#3000
1&
1+
1>
b0 !"
b1 !"
b10 !"
b11 !"
b100 !"
b101 !"
b110 !"
b111 !"
b1000 !"
1T
1S
1R
1Q
#3500
b1 ,
0&
0+
0>
b1011 2
b10 ,
0E
0@
b10 I
#4000
1&
1+
1>
b0 !"
b1 !"
b10 !"
b11 !"
b100 !"
b101 !"
b110 !"
b111 !"
b1000 !"
0S
0R
0Q
1P
1\
1[
1Y
1F!
1E!
1C!
1f!
1e!
1c!
1v!
1u!
1s!
1~!
1}!
1{!
#4500
0&
0+
0>
b1011101 2
b11 ,
0F
1E
1C
1A
b11 I
#5000
1&
1+
1>
b0 !"
b1 !"
b10 !"
b11 !"
b100 !"
b101 !"
b110 !"
b111 !"
b1000 !"
1S
1Q
0\
0[
0Y
1d
1c
1a
#5500
0&
0+
0>
b100000 2
b100 ,
0G
0E
0D
0C
1B
0A
b100 I
#6000
1&
1+
1>
b0 !"
b1 !"
b10 !"
b11 !"
b100 !"
b101 !"
b110 !"
b111 !"
b1000 !"
1R
0d
0c
0a
1l
1k
1i
1N!
1M!
1K!
0F!
0E!
0C!
#6500
0&
0+
0>
b11110011 2
b101 ,
1G
1F
1C
1A
1@
b101 I
#7000
1&
1+
1>
b0 !"
b1 !"
b10 !"
b11 !"
b100 !"
b101 !"
b110 !"
b111 !"
b1000 !"
0T
0R
1O
0l
0k
0i
1t
1s
1q
1_
1A!
0f!
0e!
0c!
1a!
0v!
0u!
0s!
1q!
0~!
0}!
0{!
1y!
#7500
0&
0+
0>
b111110 2
b110 ,
0G
1E
1D
0A
0@
b110 I
#8000
1&
1+
1>
b0 !"
b1 !"
b10 !"
b11 !"
b100 !"
b101 !"
b110 !"
b111 !"
b1000 !"
0S
0Q
0P
0O
1N
0_
1g
0t
0s
0q
1|
1{
1y
1V!
1U!
1S!
0N!
0M!
0K!
1I!
0A!
1[
1Z
1Y
1X
1W
1E!
1D!
1C!
1B!
1A!
1n!
1m!
1k!
1e!
1d!
1c!
1b!
1u!
1t!
1s!
1r!
1}!
1|!
1{!
1z!
#8500
0&
0+
0>
b11100101 2
b111 ,
1G
0F
0D
0C
1A
1@
b111 I
#9000
1&
1+
1>
b0 !"
b1 !"
b10 !"
b11 !"
b100 !"
b101 !"
b110 !"
b111 !"
b1000 !"
1S
1Q
1P
0[
0Z
0Y
0X
0W
1c
1b
1a
1`
1_
0g
1o
0|
0{
0y
1&!
1%!
1#!
#9500
0&
0+
0>
b11 2
b1000 ,
1F
0E
0B
0A
0@
b1000 I
#10000
1&
1+
1>
b0 !"
b1 !"
b10 !"
b11 !"
b100 !"
b101 !"
b110 !"
b111 !"
b1000 !"
1\
1[
0c
0b
0a
0`
0_
1k
1j
1i
1h
1g
0o
1w
0&!
0%!
0#!
1.!
1-!
1+!
1^!
1]!
1[!
0V!
0U!
0S!
1Q!
1M!
1L!
1K!
1J!
1F!
0D!
0C!
0B!
0A!
0n!
0m!
0k!
1i!
#10500
0&
0+
0>
b1100 2
0G
0F
1E
1D
b10101011 H
1=
1<
1:
18
16
#11000
1&
1+
1>
b0 !"
b1 !"
b10 !"
b11 !"
b100 !"
b101 !"
b110 !"
b111 !"
b1000 !"
1'
b1001 ,
0S
1R
0\
0[
1Z
1Y
1d
1c
0k
0j
0i
0h
0g
1s
1r
1q
1p
1o
0w
1!!
0.!
0-!
0+!
16!
15!
13!
0F!
0E!
1D!
1C!
#11500
0&
0+
0>
b1110100 2
b1010 ,
0D
1C
1B
1A
b10101101 H
0<
1;
#12000
1&
1+
1>
b0 !"
b1 !"
b10 !"
b11 !"
b100 !"
b101 !"
b110 !"
b111 !"
b1000 !"
b10101101 3
b1 /
1T
0R
0Z
0Y
0d
0c
1b
1a
1l
1k
0s
0r
0q
0p
0o
1{
1z
1y
1x
1w
0!!
1)!
06!
05!
03!
1>!
1=!
1;!
0^!
0]!
0[!
1Y!
1U!
1T!
1S!
1R!
1N!
0L!
0K!
0J!
0I!
0e!
0b!
0a!
1m!
1l!
1k!
1j!
#12500
0&
0+
0>
b1111001 2
b1011 ,
1G
0E
1D
b10101001 H
0;
#13000
1&
1+
1>
b0 !"
b1 !"
b10 !"
b11 !"
b100 !"
b101 !"
b110 !"
b111 !"
b1000 !"
b10101001 3
b10 /
1R
0Q
0P
1O
0b
0a
0l
0k
1j
1i
1t
1s
0{
0z
0y
0x
0w
1%!
1$!
1#!
1"!
1!!
0)!
11!
0>!
0=!
0;!
0N!
0M!
1L!
1K!
0D!
0C!
1>!
1<!
1;!
1:!
18!
1~!
0}!
0y!
1x!
#13500
0&
0+
0>
b1 2
b1100 ,
0D
0C
0B
0A
b11011010 H
0=
1<
19
08
17
#14000
1&
1+
1>
b0 !"
b1 !"
b10 !"
b11 !"
b100 !"
b101 !"
b110 !"
b111 !"
b1000 !"
b11011010 3
b11 /
1S
0R
1Q
1P
0O
1\
0j
0i
0t
0s
1r
1q
1|
1{
0%!
0$!
0#!
0"!
0!!
1-!
1,!
1+!
1*!
1)!
01!
0>!
0<!
0;!
0:!
19!
08!
0~!
1}!
1y!
0x!
1]!
1\!
1[!
1Z!
1V!
0T!
0S!
0R!
0Q!
1F!
#14500
0&
0+
0>
b110000 2
b1101 ,
0G
1C
1B
b10101100 H
0<
1;
09
18
07
#15000
1&
1+
1>
b0 !"
b1 !"
b10 !"
b11 !"
b100 !"
b101 !"
b110 !"
b111 !"
b1000 !"
b10101100 3
b100 /
0T
0S
1R
0\
1X
1W
1d
0r
0q
0|
0{
1z
1y
1&!
1%!
0-!
0,!
0+!
0*!
0)!
15!
14!
13!
12!
11!
09!
0V!
0U!
1T!
1S!
0L!
0K!
0F!
1B!
1A!
0d!
0c!
1b!
1a!
#15500
0&
0+
0>
b101110 2
b1110 ,
1F
1E
1D
0C
b10101110 H
1<
#16000
1&
1+
1>
b0 !"
b1 !"
b10 !"
b11 !"
b100 !"
b101 !"
b110 !"
b111 !"
b1000 !"
b10101110 3
b101 /
1S
0Q
0P
1[
1Z
1Y
0X
0d
1`
1_
1l
0z
0y
0&!
0%!
1$!
1#!
1.!
1-!
05!
04!
03!
02!
01!
1=!
1<!
1;!
1:!
19!
1^!
0\!
0[!
0Z!
0Y!
1N!
0m!
0j!
0i!
0u!
0t!
0s!
#16500
0&
0+
0>
b10100100 2
b1111 ,
0F
0D
1@
b10010101 H
1=
0<
0:
19
08
#17000
1&
1+
1>
b0 !"
b1 !"
b10 !"
b11 !"
b100 !"
b101 !"
b110 !"
b111 !"
b1000 !"
b10010101 3
b110 /
0R
1P
0[
0Z
0Y
0W
1c
1b
1a
0`
0l
1h
1g
1t
0$!
0#!
0.!
0-!
1,!
1+!
16!
15!
0=!
0<!
0;!
0:!
09!
0}!
0|!
0{!
0^!
0]!
1\!
1[!
0T!
0S!
0N!
1J!
1I!
1E!
1D!
1C!
0B!
#17500
0&
0+
0>
b1110110 2
b10000 ,
1F
1C
1A
0@
b10010010 H
0=
1<
0;
#18000
1&
1+
1>
b0 !"
b1 !"
b10 !"
b11 !"
b100 !"
b101 !"
b110 !"
b111 !"
b1000 !"
b10010010 3
b111 /
1T
0S
1R
0P
0c
0b
0a
0_
1k
1j
1i
0h
0t
1p
1o
1|
0,!
0+!
06!
05!
14!
13!
1>!
1=!
1V!
0E!
0D!
0C!
0A!
#18500
0&
0+
0>
b10000100 2
b10001 ,
0F
0C
0B
0A
1@
b10000100 H
0<
1;
09
#19000
1&
1+
1>
b0 !"
b1 !"
b10 !"
b11 !"
b100 !"
b101 !"
b110 !"
b111 !"
b1000 !"
b10000100 3
b1000 /
0T
1P
0k
0j
0i
0g
1s
1r
1q
0p
0|
1x
1w
1&!
04!
03!
0>!
0=!
1<!
1;!
0\!
0[!
0V!
1R!
1Q!
1M!
1L!
1K!
0J!
1e!
1d!
1c!
0b!
0l!
0k!
1j!
1i!
#19500
0&
0+
0>
b1010001 2
b10010 ,
1G
0E
1C
1A
0@
b10010100 H
19
#20000
1&
1+
1>
b0 !"
b1 !"
b10 !"
b11 !"
b100 !"
b101 !"
b110 !"
b111 !"
b1000 !"
b10010100 3
b1001 /
1T
1S
0R
1Q
1\
1X
1V
0s
0r
0q
0o
1{
1z
1y
0x
0&!
1"!
1!!
1.!
0<!
0;!
1^!
0M!
0L!
0K!
0I!
1F!
1B!
1@!
1f!
0e!
0d!
0c!
1b!
0a!
1`!
1v!
0q!
1p!
1~!
0y!
1x!
#20500
0&
0+
0>
b11010110 2
b10011 ,
0G
1F
1E
1@
b11000010 H
1<
0;
09
17
#21000
1&
1+
1>
b0 !"
b1 !"
b10 !"
b11 !"
b100 !"
b101 !"
b110 !"
b111 !"
b1000 !"
b11000010 3
b1010 /
0T
1R
0Q
0P
1O
0\
0X
0V
1d
1`
1^
0{
0z
0y
0w
1%!
1$!
1#!
0"!
0.!
1*!
1)!
16!
0^!
1Z!
1Y!
1U!
1T!
1S!
0R!
#21500
0&
0+
0>
b1110000 2
b10100 ,
0F
0E
1B
0@
b11001110 H
1;
1:
#22000
1&
1+
1>
b0 !"
b1 !"
b10 !"
b11 !"
b100 !"
b101 !"
b110 !"
b111 !"
b1000 !"
b11001110 3
b1011 /
1T
0S
0d
0`
0^
1l
1h
1f
0%!
0$!
0#!
0!!
1-!
1,!
1+!
0*!
06!
12!
11!
1>!
0U!
0T!
0S!
0Q!
1N!
1J!
1H!
0F!
0B!
0@!
#22500
0&
0+
0>
b110101 2
b10101 ,
1G
1E
0A
b11001101 H
1=
0<
#23000
1&
1+
1>
b0 !"
b1 !"
b10 !"
b11 !"
b100 !"
b101 !"
b110 !"
b111 !"
b1000 !"
b11001101 3
b1100 /
1S
0R
1Q
1\
1Z
1X
1W
0l
0h
0f
1t
1p
1n
0-!
0,!
0+!
0)!
15!
14!
13!
02!
0>!
1:!
19!
1]!
1\!
1[!
0Z!
1F!
1D!
1B!
1A!
1m!
1l!
1k!
0j!
#23500
0&
0+
0>
b10000 2
b10110 ,
0G
0E
0B
b11010100 H
0=
0:
19
#24000
1&
1+
1>
b0 !"
b1 !"
b10 !"
b11 !"
b100 !"
b101 !"
b110 !"
b111 !"
b1000 !"
b11010100 3
b1101 /
0T
0S
0\
0Z
0W
1d
1b
1`
1_
0t
0p
0n
1|
1x
1v
05!
04!
03!
01!
1=!
1<!
1;!
0:!
0]!
0\!
0[!
0Y!
1V!
1R!
1P!
0N!
0J!
0H!
1d!
1a!
0`!
1n!
0m!
0l!
0k!
1j!
0i!
1h!
#24500
0&
0+
0>
b100011 2
b10111 ,
1G
1F
0C
1B
b11010000 H
0;
#25000
1&
1+
1>
b0 !"
b1 !"
b10 !"
b11 !"
b100 !"
b101 !"
b110 !"
b111 !"
b1000 !"
b11010000 3
b1110 /
1S
1R
0Q
1\
1[
0X
1W
0d
0b
0_
1l
1j
1h
1g
0|
0x
0v
1&!
1"!
1~
0=!
0<!
0;!
09!
1N!
1L!
1J!
1I!
1E!
0D!
0B!
#25500
0&
0+
0>
b11100111 2
b11000 ,
1E
1A
1@
b11001110 H
1<
1;
1:
09
#26000
1&
1+
1>
b0 !"
b1 !"
b10 !"
b11 !"
b100 !"
b101 !"
b110 !"
b111 !"
b1000 !"
b11001110 3
b1111 /
1Q
0\
0[
0W
1d
1c
0`
1_
0l
0j
0g
1t
1r
1p
1o
0&!
0"!
0~
1.!
1*!
1(!
1^!
1Z!
1X!
0V!
0R!
0P!
#26500
0&
0+
0>
b111011 2
b11001 ,
0E
1D
1C
0A
0@
b11010111 H
1=
0:
19
#27000
1&
1+
1>
b0 !"
b1 !"
b10 !"
b11 !"
b100 !"
b101 !"
b110 !"
b111 !"
b1000 !"
b11010111 3
b10000 /
1T
0Q
1\
1[
1Y
1X
1W
0d
0c
0_
1l
1k
0h
1g
0t
0r
0o
1|
1z
1x
1w
0.!
0*!
0(!
16!
12!
10!
1V!
1T!
1R!
1Q!
1M!
0L!
0J!
1C!
1B!
1e!
0d!
1c!
#27500
0&
0+
0>
b1101101 2
b11010 ,
0F
1E
0C
1A
b11001111 H
1:
09
#28000
1&
1+
1>
b0 !"
b1 !"
b10 !"
b11 !"
b100 !"
b101 !"
b110 !"
b111 !"
b1000 !"
b11001111 3
b10001 /
0S
0\
0[
0Y
0X
0W
1d
1c
1a
1`
1_
0l
0k
0g
1t
1s
0p
1o
0|
0z
0w
1&!
1$!
1"!
1!!
06!
02!
00!
1>!
1:!
18!
0^!
0Z!
0X!
1l!
1i!
0h!
1u!
1s!
1q!
0p!
#28500
0&
0+
0>
b110100 2
b11011 ,
0G
0D
1C
0A
b11001100 H
0=
0<
#29000
1&
1+
1>
b0 !"
b1 !"
b10 !"
b11 !"
b100 !"
b101 !"
b110 !"
b111 !"
b1000 !"
b11001100 3
b10010 /
0R
1Z
1X
1W
0d
0c
0a
0`
0_
1l
1k
1i
1h
1g
0t
0s
0o
1|
1{
0x
1w
0&!
0$!
0!!
1.!
1,!
1*!
1)!
0>!
0:!
08!
1}!
1{!
1y!
0x!
1^!
1\!
1Z!
1Y!
1U!
0T!
0R!
1K!
1J!
0F!
0E!
1D!
0C!
#29500
0&
0+
0>
b1100001 2
b11100 ,
1G
0E
0C
1A
b10110000 H
0;
0:
19
18
07
#30000
1&
1+
1>
b0 !"
b1 !"
b10 !"
b11 !"
b100 !"
b101 !"
b110 !"
b111 !"
b1000 !"
b10110000 3
b10011 /
0T
1R
1P
0O
1\
0Z
0X
1V
1b
1`
1_
0l
0k
0i
0h
0g
1t
1s
1q
1p
1o
0|
0{
0w
1&!
1%!
0"!
1!!
0.!
0,!
0)!
16!
14!
12!
11!
1F!
0D!
0B!
1@!
0\
0W
0V
0F!
1D!
1B!
0@!
0e!
0c!
0b!
1`!
0u!
0s!
0r!
1p!
1e!
1c!
1b!
0`!
1u!
1s!
1r!
0p!
0}!
0{!
0z!
1x!
1}!
1{!
1z!
0x!
#30500
0&
0+
0>
b10001001 2
b11101 ,
1D
0B
0A
1@
b10100001 H
1=
09
